uuid7.py
uuid7_standard-1.1.0.dist-info/METADATA
uuid7_standard-1.1.0.dist-info/WHEEL
uuid7_standard-1.1.0.dist-info/RECORD
