Metadata-Version: 2.4
Name: uuid7-standard
Version: 1.1.0
Summary: UUIDv7 with the final standard. Not to be confused with the uuid7 package on pypi, based on a draft version that was very different.
Project-URL: Homepage, https://git.zi.fi/LeoVasanko/uuid7-standard
Project-URL: Repository, https://github.com/LeoVasanko/uuid7-standard
Author: Leo Vasanko
Keywords: database,ordering,primary-key,timestamp,uuid,uuid7
Classifier: Development Status :: 5 - Production/Stable
Classifier: Intended Audience :: Developers
Classifier: License :: OSI Approved :: MIT License
Classifier: License :: Public Domain
Classifier: Programming Language :: Python :: 3
Classifier: Topic :: Software Development :: Libraries :: Python Modules
Classifier: Topic :: Utilities
Requires-Python: >=3.8
